{
	"$schema": "http://schema.management.azure.com/schemas/2015-01-01/deploymentTemplate.json#",
	"contentVersion": "1.0.0.0",
	"parameters": {
		"factoryName": {
			"type": "string",
			"metadata": "Nombre de instancia de Data Factory",
			"defaultValue": "ideasystems-adf"
		},
		"AzureBlobStorage1_connectionString": {
			"type": "secureString",
			"metadata": "Cadena protegida para \"connectionString\"de \"AzureBlobStorage1\""
		}
	},
	"variables": {
		"factoryId": "[concat('Microsoft.DataFactory/factories/', parameters('factoryName'))]"
	},
	"resources": [
		{
			"name": "[concat(parameters('factoryName'), '/pipeline1')]",
			"type": "Microsoft.DataFactory/factories/pipelines",
			"apiVersion": "2018-06-01",
			"properties": {
				"activities": [
					{
						"name": "Data flow1",
						"type": "ExecuteDataFlow",
						"dependsOn": [],
						"policy": {
							"timeout": "0.12:00:00",
							"retry": 0,
							"retryIntervalInSeconds": 30,
							"secureOutput": false,
							"secureInput": false
						},
						"userProperties": [],
						"typeProperties": {
							"dataflow": {
								"referenceName": "dataflow1",
								"type": "DataFlowReference",
								"parameters": {},
								"datasetParameters": {
									"source1": {},
									"sink1": {}
								}
							},
							"staging": {},
							"compute": {
								"coreCount": 8,
								"computeType": "General"
							},
							"traceLevel": "Fine"
						}
					},
					{
						"name": "Fail1",
						"type": "Fail",
						"dependsOn": [
							{
								"activity": "Data flow1",
								"dependencyConditions": [
									"Failed"
								]
							}
						],
						"userProperties": [],
						"typeProperties": {
							"message": "Error",
							"errorCode": "213"
						}
					}
				],
				"policy": {
					"elapsedTimeMetric": {}
				},
				"annotations": [
					"hgghgh"
				],
				"lastPublishTime": "2024-03-25T14:58:20Z"
			},
			"dependsOn": [
				"[concat(variables('factoryId'), '/dataflows/dataflow1')]"
			]
		},
		{
			"name": "[concat(parameters('factoryName'), '/DelimitedText1')]",
			"type": "Microsoft.DataFactory/factories/datasets",
			"apiVersion": "2018-06-01",
			"properties": {
				"linkedServiceName": {
					"referenceName": "AzureBlobStorage1",
					"type": "LinkedServiceReference"
				},
				"annotations": [],
				"type": "DelimitedText",
				"typeProperties": {
					"location": {
						"type": "AzureBlobStorageLocation",
						"container": "ideasystemscontenedorsa"
					},
					"columnDelimiter": ",",
					"escapeChar": "\\",
					"firstRowAsHeader": true,
					"quoteChar": "\""
				},
				"schema": [
					{
						"name": "ELECTRICA SILVA.",
						"type": "String"
					},
					{
						"name": "Prop_1",
						"type": "String"
					},
					{
						"name": "Prop_2",
						"type": "String"
					},
					{
						"name": "Prop_3",
						"type": "String"
					},
					{
						"name": "Prop_4",
						"type": "String"
					},
					{
						"name": "Prop_5",
						"type": "String"
					},
					{
						"name": "Prop_6",
						"type": "String"
					},
					{
						"name": "Prop_7",
						"type": "String"
					},
					{
						"name": "Prop_8",
						"type": "String"
					},
					{
						"name": "Prop_9",
						"type": "String"
					}
				]
			},
			"dependsOn": [
				"[concat(variables('factoryId'), '/linkedServices/AzureBlobStorage1')]"
			]
		},
		{
			"name": "[concat(parameters('factoryName'), '/DelimitedText2')]",
			"type": "Microsoft.DataFactory/factories/datasets",
			"apiVersion": "2018-06-01",
			"properties": {
				"linkedServiceName": {
					"referenceName": "AzureBlobStorage1",
					"type": "LinkedServiceReference"
				},
				"annotations": [],
				"type": "DelimitedText",
				"typeProperties": {
					"location": {
						"type": "AzureBlobStorageLocation",
						"container": "ideasystemscontenedorsa"
					},
					"columnDelimiter": ",",
					"escapeChar": "\\",
					"firstRowAsHeader": true,
					"quoteChar": "\""
				},
				"schema": [
					{
						"name": "ELECTRICA SILVA.",
						"type": "String"
					},
					{
						"name": "Prop_1",
						"type": "String"
					},
					{
						"name": "Prop_2",
						"type": "String"
					},
					{
						"name": "Prop_3",
						"type": "String"
					},
					{
						"name": "Prop_4",
						"type": "String"
					},
					{
						"name": "Prop_5",
						"type": "String"
					},
					{
						"name": "Prop_6",
						"type": "String"
					},
					{
						"name": "Prop_7",
						"type": "String"
					},
					{
						"name": "Prop_8",
						"type": "String"
					},
					{
						"name": "Prop_9",
						"type": "String"
					}
				]
			},
			"dependsOn": [
				"[concat(variables('factoryId'), '/linkedServices/AzureBlobStorage1')]"
			]
		},
		{
			"name": "[concat(parameters('factoryName'), '/Json1')]",
			"type": "Microsoft.DataFactory/factories/datasets",
			"apiVersion": "2018-06-01",
			"properties": {
				"linkedServiceName": {
					"referenceName": "AzureBlobStorage1",
					"type": "LinkedServiceReference"
				},
				"annotations": [],
				"type": "Json",
				"typeProperties": {
					"location": {
						"type": "AzureBlobStorageLocation",
						"container": "ideasystemscontenedorsa"
					}
				},
				"schema": {}
			},
			"dependsOn": [
				"[concat(variables('factoryId'), '/linkedServices/AzureBlobStorage1')]"
			]
		},
		{
			"name": "[concat(parameters('factoryName'), '/AzureBlobStorage1')]",
			"type": "Microsoft.DataFactory/factories/linkedServices",
			"apiVersion": "2018-06-01",
			"properties": {
				"annotations": [],
				"type": "AzureBlobStorage",
				"typeProperties": {
					"connectionString": "[parameters('AzureBlobStorage1_connectionString')]"
				}
			},
			"dependsOn": []
		},
		{
			"name": "[concat(parameters('factoryName'), '/dataflow1')]",
			"type": "Microsoft.DataFactory/factories/dataflows",
			"apiVersion": "2018-06-01",
			"properties": {
				"type": "MappingDataFlow",
				"typeProperties": {
					"sources": [
						{
							"dataset": {
								"referenceName": "DelimitedText2",
								"type": "DatasetReference"
							},
							"name": "source1"
						}
					],
					"sinks": [
						{
							"dataset": {
								"referenceName": "Json1",
								"type": "DatasetReference"
							},
							"name": "sink1",
							"rejectedDataLinkedService": {
								"referenceName": "AzureBlobStorage1",
								"type": "LinkedServiceReference"
							}
						}
					],
					"transformations": [
						{
							"name": "derivedColumn1"
						}
					],
					"scriptLines": [
						"source(output(",
						"          {ELECTRICA SILVA.} as string,",
						"          Prop_1 as string,",
						"          Prop_2 as string,",
						"          Prop_3 as string,",
						"          Prop_4 as string,",
						"          Prop_5 as string,",
						"          Prop_6 as string,",
						"          Prop_7 as string,",
						"          Prop_8 as string,",
						"          Prop_9 as string",
						"     ),",
						"     allowSchemaDrift: true,",
						"     validateSchema: false,",
						"     limit: 100,",
						"     ignoreNoFilesFound: false) ~> source1",
						"source1 derive(Prop_1 = @(campo=Prop_2),",
						"          columna3 = array(Prop_1,Prop_4)) ~> derivedColumn1",
						"derivedColumn1 sink(allowSchemaDrift: true,",
						"     validateSchema: true,",
						"     partitionFileNames:['json111'],",
						"     skipDuplicateMapInputs: true,",
						"     skipDuplicateMapOutputs: true,",
						"     partitionBy('hash', 1)) ~> sink1"
					]
				}
			},
			"dependsOn": [
				"[concat(variables('factoryId'), '/datasets/DelimitedText2')]",
				"[concat(variables('factoryId'), '/datasets/Json1')]",
				"[concat(variables('factoryId'), '/linkedServices/AzureBlobStorage1')]"
			]
		}
	]
}